a_pandas_ex_regex_enhancements/LICENSE
a_pandas_ex_regex_enhancements/README.MD
a_pandas_ex_regex_enhancements/__init__.py
a_pandas_ex_regex_enhancements/requirements.txt
a_pandas_ex_regex_enhancements/thirdparty.json
a_pandas_ex_regex_enhancements-0.11.dist-info/LICENSE.rst
a_pandas_ex_regex_enhancements-0.11.dist-info/METADATA
a_pandas_ex_regex_enhancements-0.11.dist-info/WHEEL
a_pandas_ex_regex_enhancements-0.11.dist-info/top_level.txt
a_pandas_ex_regex_enhancements-0.11.dist-info/RECORD
