Metadata-Version: 2.1
Name: a_pandas_ex_regex_enhancements
Version: 0.11
Summary: Get repeated capture groups, search without having to fear Exceptions in any df/Series, convert results to appropriate dtypes, use fast Trie regex
Home-page: https://github.com/hansalemaos/a_pandas_ex_regex_enhancements
Author: Johannes Fischer
Author-email: <aulasparticularesdealemaosp@gmail.com>
License: MIT
Keywords: pandas,dtypes,regex,regular expressions,re
Classifier: Development Status :: 4 - Beta
Classifier: Programming Language :: Python :: 3 :: Only
Classifier: Programming Language :: Python :: 3.9
Classifier: Topic :: Scientific/Engineering :: Visualization
Classifier: Topic :: Software Development :: Libraries :: Python Modules
Classifier: Topic :: Text Editors :: Text Processing
Classifier: Topic :: Text Processing :: General
Classifier: Topic :: Text Processing :: Indexing
Classifier: Topic :: Text Processing :: Filters
Classifier: Topic :: Utilities
License-File: LICENSE.rst
